{
  "pageNumber": 1,
  "filters": [
    {
      "name": "Trade Select",
      "key": "trade_select.id",
      "facets": [
        {
          "name": "Trade Select",
          "value": 1,
          "description": "Exclusive subscriber pricing",
          "count": 484,
          "is_checked": false
        }
      ]
    },
    {
      "name": "Roast Level",
      "key": "roast_level.id",
      "facets": [
        {
          "name": "Light",
          "value": 147,
          "description": null,
          "count": 34,
          "is_checked": false
        },
        {
          "name": "Light-Medium",
          "value": 158,
          "description": null,
          "count": 121,
          "is_checked": false
        },
        {
          "name": "Medium",
          "value": 156,
          "description": null,
          "count": 270,
          "is_checked": false
        },
        {
          "name": "Medium-Dark",
          "value": 153,
          "description": null,
          "count": 52,
          "is_checked": false
        },
        {
          "name": "Dark",
          "value": 174,
          "description": null,
          "count": 23,
          "is_checked": false
        },
        {
          "name": "Extra-Dark",
          "value": 683,
          "description": null,
          "count": 10,
          "is_checked": false
        }
      ]
    },
    {
      "name": "Coffee Tastes Like",
      "key": "coffee_tastes_like.id",
      "facets": [
        {
          "name": "Berry Fruit",
          "value": 306,
          "description": null,
          "count": 49,
          "is_checked": false
        },
        {
          "name": "Brown Sugar",
          "value": 395,
          "description": null,
          "count": 40,
          "is_checked": false
        },
        {
          "name": "Citrus",
          "value": 401,
          "description": null,
          "count": 40,
          "is_checked": false
        },
        {
          "name": "Earthiness",
          "value": 400,
          "description": null,
          "count": 6,
          "is_checked": false
        },
        {
          "name": "Florals",
          "value": 396,
          "description": null,
          "count": 16,
          "is_checked": false
        },
        {
          "name": "Milk Chocolate",
          "value": 398,
          "description": null,
          "count": 148,
          "is_checked": false
        },
        {
          "name": "Nut",
          "value": 302,
          "description": null,
          "count": 38,
          "is_checked": false
        },
        {
          "name": "Ripe Fruit",
          "value": 397,
          "description": null,
          "count": 76,
          "is_checked": false
        },
        {
          "name": "Roastiness",
          "value": 423,
          "description": null,
          "count": 40,
          "is_checked": false
        },
        {
          "name": "Savoriness",
          "value": 445,
          "description": null,
          "count": 1,
          "is_checked": false
        },
        {
          "name": "Spice",
          "value": 394,
          "description": null,
          "count": 15,
          "is_checked": false
        },
        {
          "name": "Sweet Vanilla",
          "value": 402,
          "description": null,
          "count": 27,
          "is_checked": false
        },
        {
          "name": "Tropical Fruit",
          "value": 289,
          "description": null,
          "count": 13,
          "is_checked": false
        }
      ]
    },
    {
      "name": "Price",
      "key": "price_bucket.id",
      "facets": [
        {
          "name": "Less than $16",
          "value": 1,
          "description": null,
          "count": 106,
          "is_checked": false
        },
        {
          "name": "$16 - $19",
          "value": 2,
          "description": null,
          "count": 128,
          "is_checked": false
        },
        {
          "name": "$19 - $22",
          "value": 3,
          "description": null,
          "count": 205,
          "is_checked": false
        },
        {
          "name": "More than $22",
          "value": 4,
          "description": null,
          "count": 71,
          "is_checked": false
        }
      ]
    },
    {
      "name": "Region",
      "key": "regions.id",
      "facets": [
        {
          "name": "Africa",
          "value": 152,
          "description": null,
          "count": 160,
          "is_checked": false
        },
        {
          "name": "Asia",
          "value": 168,
          "description": null,
          "count": 55,
          "is_checked": false
        },
        {
          "name": "Central America",
          "value": 149,
          "description": null,
          "count": 209,
          "is_checked": false
        },
        {
          "name": "North America",
          "value": 165,
          "description": null,
          "count": 16,
          "is_checked": false
        },
        {
          "name": "South America",
          "value": 155,
          "description": null,
          "count": 288,
          "is_checked": false
        }
      ]
    },
    {
      "name": "Country",
      "key": "countries.id",
      "facets": [
        {
          "name": "Brazil",
          "value": 159,
          "description": null,
          "count": 96,
          "is_checked": false
        },
        {
          "name": "Burundi",
          "value": 162,
          "description": null,
          "count": 10,
          "is_checked": false
        },
        {
          "name": "Colombia",
          "value": 154,
          "description": null,
          "count": 172,
          "is_checked": false
        },
        {
          "name": "Congo",
          "value": 188,
          "description": null,
          "count": 5,
          "is_checked": false
        },
        {
          "name": "Costa Rica",
          "value": 150,
          "description": null,
          "count": 26,
          "is_checked": false
        },
        {
          "name": "East Timor",
          "value": 208,
          "description": null,
          "count": 2,
          "is_checked": false
        },
        {
          "name": "Ecuador",
          "value": 209,
          "description": null,
          "count": 3,
          "is_checked": false
        },
        {
          "name": "El Salvador",
          "value": 170,
          "description": null,
          "count": 19,
          "is_checked": false
        },
        {
          "name": "Ethiopia",
          "value": 151,
          "description": null,
          "count": 101,
          "is_checked": false
        },
        {
          "name": "Guatemala",
          "value": 157,
          "description": null,
          "count": 71,
          "is_checked": false
        },
        {
          "name": "Honduras",
          "value": 164,
          "description": null,
          "count": 58,
          "is_checked": false
        },
        {
          "name": "Indonesia",
          "value": 167,
          "description": null,
          "count": 25,
          "is_checked": false
        },
        {
          "name": "Kenya",
          "value": 160,
          "description": null,
          "count": 11,
          "is_checked": false
        },
        {
          "name": "Mexico",
          "value": 171,
          "description": null,
          "count": 20,
          "is_checked": false
        },
        {
          "name": "Nicaragua",
          "value": 148,
          "description": null,
          "count": 30,
          "is_checked": false
        },
        {
          "name": "Panama",
          "value": 198,
          "description": null,
          "count": 4,
          "is_checked": false
        },
        {
          "name": "Papua New Guinea",
          "value": 169,
          "description": null,
          "count": 11,
          "is_checked": false
        },
        {
          "name": "Peru",
          "value": 161,
          "description": null,
          "count": 45,
          "is_checked": false
        },
        {
          "name": "Rwanda",
          "value": 163,
          "description": null,
          "count": 16,
          "is_checked": false
        },
        {
          "name": "Sulawesi",
          "value": 854,
          "description": null,
          "count": 1,
          "is_checked": false
        },
        {
          "name": "Sumatra",
          "value": 172,
          "description": null,
          "count": 15,
          "is_checked": false
        },
        {
          "name": "Tanzania",
          "value": 318,
          "description": null,
          "count": 4,
          "is_checked": false
        },
        {
          "name": "Thailand",
          "value": 429,
          "description": null,
          "count": 1,
          "is_checked": false
        },
        {
          "name": "Uganda",
          "value": 181,
          "description": null,
          "count": 1,
          "is_checked": false
        },
        {
          "name": "Various",
          "value": 433,
          "description": null,
          "count": 16,
          "is_checked": false
        }
      ]
    },
    {
      "name": "Roaster",
      "key": "brand.id",
      "facets": [
        {
          "name": "Airship",
          "value": 106,
          "description": null,
          "count": 7,
          "is_checked": false
        },
        {
          "name": "Alma",
          "value": 902,
          "description": null,
          "count": 17,
          "is_checked": false
        },
        {
          "name": "Anodyne",
          "value": 116,
          "description": null,
          "count": 7,
          "is_checked": false
        },
        {
          "name": "Atomic",
          "value": 113,
          "description": null,
          "count": 15,
          "is_checked": false
        },
        {
          "name": "Bean & Bean",
          "value": 1005,
          "description": null,
          "count": 13,
          "is_checked": false
        },
        {
          "name": "Bird Rock",
          "value": 271,
          "description": null,
          "count": 9,
          "is_checked": false
        },
        {
          "name": "Blueprint",
          "value": 229,
          "description": null,
          "count": 11,
          "is_checked": false
        },
        {
          "name": "Boxcar",
          "value": 125,
          "description": null,
          "count": 4,
          "is_checked": false
        },
        {
          "name": "Broadsheet",
          "value": 788,
          "description": null,
          "count": 8,
          "is_checked": false
        },
        {
          "name": "Caffe Vita",
          "value": 133,
          "description": null,
          "count": 10,
          "is_checked": false
        },
        {
          "name": "Cerberus",
          "value": 1054,
          "description": null,
          "count": 5,
          "is_checked": false
        },
        {
          "name": "City of Saints",
          "value": 449,
          "description": null,
          "count": 16,
          "is_checked": false
        },
        {
          "name": "Common Voice",
          "value": 955,
          "description": null,
          "count": 6,
          "is_checked": false
        },
        {
          "name": "Cuvee",
          "value": 279,
          "description": null,
          "count": 7,
          "is_checked": false
        },
        {
          "name": "DOMA",
          "value": 129,
          "description": null,
          "count": 7,
          "is_checked": false
        },
        {
          "name": "Drink Coffee Do Stuff",
          "value": 909,
          "description": null,
          "count": 10,
          "is_checked": false
        },
        {
          "name": "Dune",
          "value": 104,
          "description": null,
          "count": 11,
          "is_checked": false
        },
        {
          "name": "Equator",
          "value": 372,
          "description": null,
          "count": 12,
          "is_checked": false
        },
        {
          "name": "Feast",
          "value": 951,
          "description": null,
          "count": 8,
          "is_checked": false
        },
        {
          "name": "Gimme!",
          "value": 111,
          "description": null,
          "count": 18,
          "is_checked": false
        },
        {
          "name": "Good Citizen",
          "value": 846,
          "description": null,
          "count": 16,
          "is_checked": false
        },
        {
          "name": "Greater Goods",
          "value": 490,
          "description": null,
          "count": 7,
          "is_checked": false
        },
        {
          "name": "Highwire",
          "value": 225,
          "description": null,
          "count": 8,
          "is_checked": false
        },
        {
          "name": "Huckleberry",
          "value": 124,
          "description": null,
          "count": 14,
          "is_checked": false
        },
        {
          "name": "Irving Farm",
          "value": 99,
          "description": null,
          "count": 10,
          "is_checked": false
        },
        {
          "name": "Joe",
          "value": 220,
          "description": null,
          "count": 14,
          "is_checked": false
        },
        {
          "name": "Klatch",
          "value": 114,
          "description": null,
          "count": 9,
          "is_checked": false
        },
        {
          "name": "Kuma",
          "value": 109,
          "description": null,
          "count": 5,
          "is_checked": false
        },
        {
          "name": "Maquina",
          "value": 122,
          "description": null,
          "count": 11,
          "is_checked": false
        },
        {
          "name": "Methodical",
          "value": 670,
          "description": null,
          "count": 9,
          "is_checked": false
        },
        {
          "name": "Metric",
          "value": 118,
          "description": null,
          "count": 7,
          "is_checked": false
        },
        {
          "name": "Mother Tongue",
          "value": 896,
          "description": null,
          "count": 5,
          "is_checked": false
        },
        {
          "name": "Necessary",
          "value": 484,
          "description": null,
          "count": 4,
          "is_checked": false
        },
        {
          "name": "Novo",
          "value": 233,
          "description": null,
          "count": 11,
          "is_checked": false
        },
        {
          "name": "Onyx",
          "value": 134,
          "description": null,
          "count": 1,
          "is_checked": false
        },
        {
          "name": "Oren's",
          "value": 420,
          "description": null,
          "count": 12,
          "is_checked": false
        },
        {
          "name": "PERC",
          "value": 1052,
          "description": null,
          "count": 6,
          "is_checked": false
        },
        {
          "name": "PT's",
          "value": 211,
          "description": null,
          "count": 11,
          "is_checked": false
        },
        {
          "name": "Panther",
          "value": 107,
          "description": null,
          "count": 10,
          "is_checked": false
        },
        {
          "name": "Passenger",
          "value": 130,
          "description": null,
          "count": 9,
          "is_checked": false
        },
        {
          "name": "Peixoto",
          "value": 915,
          "description": null,
          "count": 8,
          "is_checked": false
        },
        {
          "name": "Portrait",
          "value": 906,
          "description": null,
          "count": 11,
          "is_checked": false
        },
        {
          "name": "ReAnimator",
          "value": 103,
          "description": null,
          "count": 7,
          "is_checked": false
        },
        {
          "name": "Red Bay",
          "value": 486,
          "description": null,
          "count": 4,
          "is_checked": false
        },
        {
          "name": "Red Rooster",
          "value": 491,
          "description": null,
          "count": 12,
          "is_checked": false
        },
        {
          "name": "Ritual",
          "value": 126,
          "description": null,
          "count": 1,
          "is_checked": false
        },
        {
          "name": "Roasted Record",
          "value": 1019,
          "description": null,
          "count": 4,
          "is_checked": false
        },
        {
          "name": "Sightglass",
          "value": 224,
          "description": null,
          "count": 13,
          "is_checked": false
        },
        {
          "name": "Small Planes",
          "value": 908,
          "description": null,
          "count": 9,
          "is_checked": false
        },
        {
          "name": "Sparrows",
          "value": 570,
          "description": null,
          "count": 19,
          "is_checked": false
        },
        {
          "name": "Steady State",
          "value": 912,
          "description": null,
          "count": 9,
          "is_checked": false
        },
        {
          "name": "Sterling",
          "value": 131,
          "description": null,
          "count": 9,
          "is_checked": false
        },
        {
          "name": "Temple",
          "value": 135,
          "description": null,
          "count": 7,
          "is_checked": false
        },
        {
          "name": "Verve",
          "value": 98,
          "description": null,
          "count": 10,
          "is_checked": false
        },
        {
          "name": "Wonderstate",
          "value": 222,
          "description": null,
          "count": 7,
          "is_checked": false
        }
      ]
    },
    {
      "name": "Type",
      "key": "type.id",
      "facets": [
        {
          "name": "Available Ground",
          "value": 146,
          "description": null,
          "count": 393,
          "is_checked": false
        },
        {
          "name": "Blends",
          "value": 44,
          "description": null,
          "count": 240,
          "is_checked": false
        },
        {
          "name": "Cold Brew",
          "value": 438,
          "description": null,
          "count": 151,
          "is_checked": false
        },
        {
          "name": "Decaf",
          "value": 137,
          "description": null,
          "count": 42,
          "is_checked": false
        },
        {
          "name": "Espresso",
          "value": 353,
          "description": null,
          "count": 44,
          "is_checked": false
        },
        {
          "name": "Single Origins",
          "value": 43,
          "description": null,
          "count": 270,
          "is_checked": false
        },
        {
          "name": "Water Processed Decaf",
          "value": 341,
          "description": null,
          "count": 16,
          "is_checked": false
        }
      ]
    },
    {
      "name": "Bag Weight",
      "key": "bean_weights.id",
      "facets": [
        {
          "name": "10 oz.",
          "value": 5,
          "description": null,
          "count": 64,
          "is_checked": false
        },
        {
          "name": "10.5 oz.",
          "value": 114,
          "description": null,
          "count": 12,
          "is_checked": false
        },
        {
          "name": "310 g.",
          "value": 113,
          "description": null,
          "count": 388,
          "is_checked": false
        },
        {
          "name": "325 g.",
          "value": 109,
          "description": null,
          "count": 4,
          "is_checked": false
        },
        {
          "name": "12 oz.",
          "value": 3,
          "description": null,
          "count": 10,
          "is_checked": false
        },
        {
          "name": "2 lb.",
          "value": 72,
          "description": null,
          "count": 261,
          "is_checked": false
        },
        {
          "name": "8 oz.",
          "value": 4,
          "description": null,
          "count": 2,
          "is_checked": false
        },
        {
          "name": "5 lb.",
          "value": 62,
          "description": null,
          "count": 26,
          "is_checked": false
        }
      ]
    },
    {
      "name": "Process",
      "key": "processes.id",
      "facets": [
        {
          "name": "Experimental/Other",
          "value": 899,
          "description": null,
          "count": 8,
          "is_checked": false
        },
        {
          "name": "Honey",
          "value": 698,
          "description": null,
          "count": 7,
          "is_checked": false
        },
        {
          "name": "Natural/Dry Processed",
          "value": 243,
          "description": null,
          "count": 116,
          "is_checked": false
        },
        {
          "name": "Pulped Natural",
          "value": 675,
          "description": null,
          "count": 22,
          "is_checked": false
        },
        {
          "name": "Pulped Natural/Honey",
          "value": 244,
          "description": null,
          "count": 53,
          "is_checked": false
        },
        {
          "name": "Washed",
          "value": 242,
          "description": null,
          "count": 417,
          "is_checked": false
        },
        {
          "name": "Wet-hulled",
          "value": 249,
          "description": null,
          "count": 20,
          "is_checked": false
        }
      ]
    },
    {
      "name": "Certifications",
      "key": "certifications.id",
      "facets": [
        {
          "name": "Certified Organic",
          "value": 673,
          "description": null,
          "count": 78,
          "is_checked": false
        },
        {
          "name": "Fair Trade",
          "value": 238,
          "description": null,
          "count": 46,
          "is_checked": false
        },
        {
          "name": "Kosher",
          "value": 334,
          "description": null,
          "count": 33,
          "is_checked": false
        },
        {
          "name": "Rainforest Alliance",
          "value": 323,
          "description": null,
          "count": 15,
          "is_checked": false
        }
      ]
    },
    {
      "name": "Seasonal",
      "key": "seasonal.id",
      "facets": [
        {
          "name": "Seasonal",
          "value": 897,
          "description": null,
          "count": 1,
          "is_checked": false
        }
      ]
    }
  ],
  "sorts": [
    {
      "name": "Relevance",
      "key": "sort",
      "value": "_score-desc",
      "is_checked": true
    },
    {
      "name": "Most Popular",
      "key": "sort",
      "value": "orders_count-desc",
      "is_checked": false
    },
    {
      "name": "New",
      "key": "sort",
      "value": "created_at-desc",
      "is_checked": false
    },
    {
      "name": "Highest Price",
      "key": "sort",
      "value": "price_lo_raw-desc",
      "is_checked": false
    },
    {
      "name": "Lowest Price",
      "key": "sort",
      "value": "price_lo_raw-asc",
      "is_checked": false
    }
  ],
  "clientPath": "/coffee/all-coffee",
  "pageSize": 18
}
